CHANGELOG.txt
LICENCE.txt
MANIFEST.in
README.txt
setup.py
DailyProjectFolder/__init__.py
DailyProjectFolder/hello.py
DailyProjectFolder/test.py
HelloworldJohnson.egg-info/PKG-INFO
HelloworldJohnson.egg-info/SOURCES.txt
HelloworldJohnson.egg-info/dependency_links.txt
HelloworldJohnson.egg-info/top_level.txt
MileStone/main.py